building_blocks/__init__.py
building_blocks/forms.py
building_blocks/utils.py
building_blocks/admin/__init__.py
building_blocks/admin/admin.py
building_blocks/admin/filters.py
building_blocks/admin/inlines.py
building_blocks/admin/mixins.py
building_blocks/admin/utils.py
building_blocks/contrib/__init__.py
building_blocks/contrib/admin.py
building_blocks/contrib/views.py
building_blocks/contrib/models/__init__.py
building_blocks/contrib/models/abstracts.py
building_blocks/contrib/models/querysets.py
building_blocks/contrib/templatetags/__init__.py
building_blocks/contrib/templatetags/nav_link.py
building_blocks/factories/__init__.py
building_blocks/factories/factories.py
building_blocks/factories/utils.py
building_blocks/models/__init__.py
building_blocks/models/abstracts.py
building_blocks/models/enums.py
building_blocks/models/fields.py
building_blocks/models/mixins.py
building_blocks/models/querysets.py
building_blocks/rest/__init__.py
building_blocks/rest/serializers.py
building_blocks/rest/viewsets.py
tests/__init__.py
tests/test_abstracts.py
tests/test_fields.py
tests/test_forms.py
tests/test_mixins.py
tests/test_querysets.py
tests/admin/__init__.py
tests/admin/test_EditReadonlyAdminMixin.py
tests/admin/test_utils.py
tests/factories/__init__.py
tests/factories/test_HasAutoCodeFactory.py
tests/factories/test_HasAutoSlugFactory.py
tests/factories/test_HasAvatarFactory.py
tests/factories/test_HasCoverPhotoFactory.py
tests/factories/test_HasDescriptionFactory.py
tests/factories/test_HasEmailFactory.py
tests/factories/test_HasIconFactory.py
tests/factories/test_HasNameFactory.py
tests/factories/test_HasUserFactory.py
django_building_blocks-0.1.0.dist-info/LICENSE
django_building_blocks-0.1.0.dist-info/METADATA
django_building_blocks-0.1.0.dist-info/WHEEL
django_building_blocks-0.1.0.dist-info/top_level.txt
django_building_blocks-0.1.0.dist-info/RECORD
