Metadata-Version: 2.1
Name: django-building-blocks
Version: 0.1.0
Summary: Abstract Django base models (and model class factories) to act as building blocks for rapid development of Django database models
Home-page: https://github.com/kaoslabsinc/django-building-blocks
Author: Kaos Labs Inc.
Author-email: keyvan@keyvanm.com
License: BSD-3-Clause
Keywords: django,abstract,models,factories
Platform: UNKNOWN
Classifier: Environment :: Web Environment
Classifier: Framework :: Django
Classifier: Framework :: Django :: 3.2
Classifier: Intended Audience :: Developers
Classifier: License :: OSI Approved :: BSD License
Classifier: Operating System :: OS Independent
Classifier: Programming Language :: Python
Classifier: Programming Language :: Python :: 3
Classifier: Programming Language :: Python :: 3 :: Only
Classifier: Programming Language :: Python :: 3.7
Classifier: Programming Language :: Python :: 3.8
Classifier: Programming Language :: Python :: 3.9
Classifier: Topic :: Internet :: WWW/HTTP
Classifier: Topic :: Internet :: WWW/HTTP :: Dynamic Content
License-File: LICENSE
Requires-Dist: Pillow
Requires-Dist: pygments (~=2.9)
Requires-Dist: django (>=3.2)
Requires-Dist: django-object-actions (~=3.0)
Requires-Dist: django-fsm (~=2.8)
Requires-Dist: djangorestframework (~=3.13)
Provides-Extra: test
Requires-Dist: tox ; extra == 'test'
Requires-Dist: pytest-django ; extra == 'test'
Requires-Dist: pytest-pythonpath ; extra == 'test'
Requires-Dist: pytest-freezegun ; extra == 'test'
